LICENSE.md
setup.py
Phabulous/__init__.py
Phabulous/main.py
Phabulous/run.py
PhabulousPhage.egg-info/PKG-INFO
PhabulousPhage.egg-info/SOURCES.txt
PhabulousPhage.egg-info/dependency_links.txt
PhabulousPhage.egg-info/entry_points.txt
PhabulousPhage.egg-info/requires.txt
PhabulousPhage.egg-info/top_level.txt